jupyter_shared_drive_ui/__init__.py
jupyter_shared_drive_ui-0.2.1.data/data/share/jupyter/labextensions/@jupyter/shared-drive-extension/package.json
jupyter_shared_drive_ui-0.2.1.data/data/share/jupyter/labextensions/@jupyter/shared-drive-extension/schemas/@jupyter/shared-drive-extension/package.json.orig
jupyter_shared_drive_ui-0.2.1.data/data/share/jupyter/labextensions/@jupyter/shared-drive-extension/schemas/@jupyter/shared-drive-extension/shared-link.json
jupyter_shared_drive_ui-0.2.1.data/data/share/jupyter/labextensions/@jupyter/shared-drive-extension/schemas/@jupyter/shared-drive-extension/user-menu-bar.json
jupyter_shared_drive_ui-0.2.1.data/data/share/jupyter/labextensions/@jupyter/shared-drive-extension/static/15.e8065d6ad665c16ece4c.js
jupyter_shared_drive_ui-0.2.1.data/data/share/jupyter/labextensions/@jupyter/shared-drive-extension/static/334.4f119a92b355f2ba33a3.js
jupyter_shared_drive_ui-0.2.1.data/data/share/jupyter/labextensions/@jupyter/shared-drive-extension/static/389.bcdcaead48ea561409d3.js
jupyter_shared_drive_ui-0.2.1.data/data/share/jupyter/labextensions/@jupyter/shared-drive-extension/static/953.4f119a92b355f2ba33a3.js
jupyter_shared_drive_ui-0.2.1.data/data/share/jupyter/labextensions/@jupyter/shared-drive-extension/static/remoteEntry.28fac45548ca4481f5c1.js
jupyter_shared_drive_ui-0.2.1.data/data/share/jupyter/labextensions/@jupyter/shared-drive-extension/static/style.js
jupyter_shared_drive_ui-0.2.1.data/data/share/jupyter/labextensions/@jupyter/shared-drive-extension/static/third-party-licenses.json
jupyter_shared_drive_ui-0.2.1.data/data/share/jupyter/labextensions/@jupyter/shared-drive-extension/install.json
jupyter_shared_drive_ui-0.2.1.dist-info/METADATA
jupyter_shared_drive_ui-0.2.1.dist-info/WHEEL
jupyter_shared_drive_ui-0.2.1.dist-info/licenses/LICENSE
jupyter_shared_drive_ui-0.2.1.dist-info/RECORD
